cleanifier/cptasks_kmers.py
cleanifier/cuckoo_filter_utils.py
cleanifier/dnaencode.py
cleanifier/dnaencode_fast.py
cleanifier/fastcash_info.py
cleanifier/fastcash_main.py
cleanifier/filter_windowed_cuckoo.py
cleanifier/hash_s3c_fbcbvb.py
cleanifier/hashfunctions.py
cleanifier/kmers.py
cleanifier/mask.py
cleanifier/mathutils.py
cleanifier/parameters.py
cleanifier/srhash.py
cleanifier/subtable_hashfunctions.py
cleanifier/cleanifier/cleanifier_download.py
cleanifier/cleanifier/cleanifier_filter.py
cleanifier/cleanifier/cleanifier_index.py
cleanifier/cleanifier/cleanifier_load.py
cleanifier/cleanifier/cleanifier_main.py
cleanifier/cleanifier/cleanifier_remove.py
cleanifier/cleanifier/config/filter.yaml
cleanifier/cleanifier/config/index.yaml
cleanifier/io/binaryio.py
cleanifier/io/fastaio.py
cleanifier/io/fastqio.py
cleanifier/io/filterio.py
cleanifier/io/generaldsio.py
cleanifier/io/generalio.py
cleanifier/io/hashio.py
cleanifier/io/seqio.py
cleanifier/io/textio.py
cleanifier/lowlevel/aligned_arrays.py
cleanifier/lowlevel/bitarray.py
cleanifier/lowlevel/conpro.py
cleanifier/lowlevel/debug.py
cleanifier/lowlevel/intbitarray.py
cleanifier/lowlevel/libc.py
cleanifier/lowlevel/llvm.py
cleanifier/values/set.py
cleanifier-1.1.4.dist-info/licenses/LICENSE
cleanifier-1.1.4.dist-info/METADATA
cleanifier-1.1.4.dist-info/WHEEL
cleanifier-1.1.4.dist-info/entry_points.txt
cleanifier-1.1.4.dist-info/top_level.txt
cleanifier-1.1.4.dist-info/RECORD
