Metadata-Version: 2.4
Name: cleanifier
Version: 1.1.4
Summary: fast lightweight tool to remove all reads of a species
Author-email: Jens Zentgraf <zentgraf@cs.uni-saarland.de>, Johanna Elena Schmitz <jschmitz@cs.uni-saarland.de>, Sven Rahmann <rahmann@cs.uni-saarland.de>
License: MIT License
Project-URL: Homepage, https://gitlab.com/rahmannlab/cleanifier
Project-URL: Bug Tracker, https://gitlab.com/rahmannlab/cleanifier/issues
Classifier: Programming Language :: Python :: 3
Classifier: License :: OSI Approved :: MIT License
Classifier: Operating System :: OS Independent
Classifier: Development Status :: 5 - Production/Stable
Classifier: Environment :: Console
Classifier: Intended Audience :: Science/Research
Classifier: Natural Language :: English
Classifier: Topic :: Scientific/Engineering :: Bio-Informatics
Requires-Python: >=3.12
License-File: LICENSE
Requires-Dist: numpy
Requires-Dist: numba
Requires-Dist: pytest
Requires-Dist: jsonargparse>=4.29.0
Requires-Dist: pip
Dynamic: license-file
